satysfi_notebook_tweaks/__init__.py
satysfi_notebook_tweaks/_version.py
satysfi_notebook_tweaks-0.3.0.data/data/share/jupyter/labextensions/satysfi-notebook-tweaks/package.json
satysfi_notebook_tweaks-0.3.0.data/data/share/jupyter/labextensions/satysfi-notebook-tweaks/static/131.6478063dfeaad1c17cd8.js
satysfi_notebook_tweaks-0.3.0.data/data/share/jupyter/labextensions/satysfi-notebook-tweaks/static/445.18c0de121bef2376dba8.js
satysfi_notebook_tweaks-0.3.0.data/data/share/jupyter/labextensions/satysfi-notebook-tweaks/static/747.4defc7e898de3ad364e1.js
satysfi_notebook_tweaks-0.3.0.data/data/share/jupyter/labextensions/satysfi-notebook-tweaks/static/remoteEntry.a2872b87d48f3c1f7d4c.js
satysfi_notebook_tweaks-0.3.0.data/data/share/jupyter/labextensions/satysfi-notebook-tweaks/static/style.js
satysfi_notebook_tweaks-0.3.0.data/data/share/jupyter/labextensions/satysfi-notebook-tweaks/static/third-party-licenses.json
satysfi_notebook_tweaks-0.3.0.data/data/share/jupyter/labextensions/satysfi-notebook-tweaks/install.json
satysfi_notebook_tweaks-0.3.0.dist-info/METADATA
satysfi_notebook_tweaks-0.3.0.dist-info/WHEEL
satysfi_notebook_tweaks-0.3.0.dist-info/licenses/LICENSE
satysfi_notebook_tweaks-0.3.0.dist-info/RECORD
