Metadata-Version: 2.3
Name: satysfi_notebook_tweaks
Version: 0.3.0
Dynamic: Keywords
Summary: A small tweaks for SATySFi Notebook environment.
Project-URL: Homepage, https://github.com/kyori19/satysfi-notebook-tweaks
Project-URL: Bug Tracker, https://github.com/kyori19/satysfi-notebook-tweaks/issues
Project-URL: Repository, https://github.com/kyori19/satysfi-notebook-tweaks.git
Author-email: kyori19 <kyori@accelf.net>
License: BSD 3-Clause License
License-File: LICENSE
Classifier: Framework :: Jupyter
Classifier: Framework :: Jupyter :: JupyterLab
Classifier: Framework :: Jupyter :: JupyterLab :: 4
Classifier: Framework :: Jupyter :: JupyterLab :: Extensions
Classifier: Framework :: Jupyter :: JupyterLab :: Extensions :: Prebuilt
Classifier: License :: OSI Approved :: BSD License
Classifier: Programming Language :: Python
Classifier: Programming Language :: Python :: 3
Classifier: Programming Language :: Python :: 3.8
Classifier: Programming Language :: Python :: 3.9
Classifier: Programming Language :: Python :: 3.10
Classifier: Programming Language :: Python :: 3.11
Classifier: Programming Language :: Python :: 3.12
Requires-Python: >=3.8
